extremecloudiq/__init__.py
extremecloudiq/api_client.py
extremecloudiq/configuration.py
extremecloudiq/exceptions.py
extremecloudiq/rest.py
extremecloudiq/api/__init__.py
extremecloudiq/api/account_api.py
extremecloudiq/api/afc_endpoint_api.py
extremecloudiq/api/alert_api.py
extremecloudiq/api/application_api.py
extremecloudiq/api/authentication_api.py
extremecloudiq/api/authorization_api.py
extremecloudiq/api/client_api.py
extremecloudiq/api/configuration___authentication_api.py
extremecloudiq/api/configuration___basic_api.py
extremecloudiq/api/configuration___certificate_api.py
extremecloudiq/api/configuration___deployment_api.py
extremecloudiq/api/configuration___network_api.py
extremecloudiq/api/configuration___policy_api.py
extremecloudiq/api/configuration___user_management_api.py
extremecloudiq/api/copilot___anomalies_api.py
extremecloudiq/api/copilot___connectivity_experience_api.py
extremecloudiq/api/device_api.py
extremecloudiq/api/essentials___extreme_location_api.py
extremecloudiq/api/hiq_api.py
extremecloudiq/api/location_api.py
extremecloudiq/api/log_api.py
extremecloudiq/api/misc_api.py
extremecloudiq/api/network_policy_api.py
extremecloudiq/api/network_scorecard_api.py
extremecloudiq/api/nos_api.py
extremecloudiq/api/notification_api.py
extremecloudiq/api/operation_api.py
extremecloudiq/api/packet_capture_api.py
extremecloudiq/api/thread_api.py
extremecloudiq/api/user_api.py
extremecloudiq/models/__init__.py
extremecloudiq/models/client_health.py
extremecloudiq/models/device_health.py
extremecloudiq/models/essentials_eloc_last_known_location.py
extremecloudiq/models/inline_object.py
extremecloudiq/models/inline_object1.py
extremecloudiq/models/inline_object2.py
extremecloudiq/models/network_health.py
extremecloudiq/models/paged_xiq_accounting_log.py
extremecloudiq/models/paged_xiq_active_directory_server.py
extremecloudiq/models/paged_xiq_alert.py
extremecloudiq/models/paged_xiq_application.py
extremecloudiq/models/paged_xiq_audit_log.py
extremecloudiq_api-24.6.0.74.dist-info/METADATA
extremecloudiq_api-24.6.0.74.dist-info/WHEEL
extremecloudiq_api-24.6.0.74.dist-info/top_level.txt
extremecloudiq_api-24.6.0.74.dist-info/RECORD
