Metadata-Version: 2.1
Name: extremecloudiq-api
Version: 24.6.0.74
Summary: ExtremeCloud IQ API
Home-page: UNKNOWN
Author: Extreme Networks Support
Author-email: support@extremenetworks.com
License: Apache 2.0
Keywords: OpenAPI,OpenAPI-Generator,ExtremeCloud IQ API
Platform: UNKNOWN
Requires-Dist: urllib3 (>=1.15)
Requires-Dist: six (>=1.10)
Requires-Dist: certifi
Requires-Dist: python-dateutil
